arduck/__init__.py
arduck/__init__.pyi
arduck/__main__.py
arduck/cli.py
arduck/py.typed
arduck/tokenizer.py
arduck/arduino/__init__.py
arduck/arduino/keyboard.py
arduck/modules/__init__.py
arduck/modules/ansi.py
arduck/modules/log.py
arduck/modules/metadata.py
arduck/modules/preset.py
arduck/modules/template.py
arduck/modules/parsing/__init__.py
arduck/modules/parsing/parents.py
arduck/modules/parsing/parsers/__init__.py
arduck/modules/parsing/parsers/main.py
arduck/parsers/__init__.py
arduck/parsers/main.py
arduck/parsers/types.py
arduck/parsers/presets/__init__.py
arduck/parsers/presets/types.py
arduck/parsers/presets/win/__init__.py
arduck/parsers/presets/win/sclogon.py
arduck/presets/win/aterm.py
arduck/presets/win/run.py
arduck/presets/win/sclogon.py
arduck/templates/any
arduck/templates/_components/base
arduck/templates/win/alt
arduck-0.0.6.dist-info/licenses/LICENSE
arduck-0.0.6.dist-info/METADATA
arduck-0.0.6.dist-info/WHEEL
arduck-0.0.6.dist-info/entry_points.txt
arduck-0.0.6.dist-info/top_level.txt
arduck-0.0.6.dist-info/RECORD
