Metadata-Version: 2.4
Name: arduck
Version: 0.0.6
Summary: Easy-to-use keystroke injection payload generator for the Arduino.
Author-email: Stefano Cuizza <stefano.cuizza@protonmail.com>
Maintainer-email: Stefano Cuizza <stefano.cuizza@protonmail.com>
License:                     GNU GENERAL PUBLIC LICENSE
Project-URL: Github, https://github.com/x55xaa/arduck
Keywords: arduino,keyboard,keystroke injection,rubber
Classifier: Development Status :: 4 - Beta
Classifier: Intended Audience :: End Users/Desktop
Classifier: License :: OSI Approved :: GNU General Public License v3 (GPLv3)
Classifier: Operating System :: MacOS
Classifier: Operating System :: Microsoft :: Windows
Classifier: Operating System :: POSIX :: Linux
Requires-Python: >=3.12
License-File: LICENSE
Requires-Dist: colorama
Requires-Dist: jinja2
Provides-Extra: docs
Requires-Dist: myst_parser; extra == "docs"
Requires-Dist: sphinx; extra == "docs"
Requires-Dist: sphinx-argparse; extra == "docs"
Requires-Dist: sphinx_autodoc_typehints; extra == "docs"
Requires-Dist: sphinx_rtd_theme; extra == "docs"
Provides-Extra: testing
Requires-Dist: pylint; extra == "testing"
Requires-Dist: pytest; extra == "testing"
Requires-Dist: pytest-cov; extra == "testing"
Requires-Dist: ruff; extra == "testing"
Requires-Dist: tox; extra == "testing"
Dynamic: license-file
